fake_mesh/__init__.py
fake_mesh/ca.cert.pem
fake_mesh/ca.key.pem
fake_mesh/key_helper.py
fake_mesh/server.cert.pem
fake_mesh/server.key.pem
fake_mesh/server.py
fake_mesh/wsgi_app.py
fake_mesh/wsgi_helpers.py
Fake_Mesh-0.4.0.dist-info/LICENSE
Fake_Mesh-0.4.0.dist-info/METADATA
Fake_Mesh-0.4.0.dist-info/WHEEL
Fake_Mesh-0.4.0.dist-info/top_level.txt
Fake_Mesh-0.4.0.dist-info/RECORD
