Metadata-Version: 2.1
Name: Fake-Mesh
Version: 0.4.0
Summary: A fake implementation of NHS Digital MESH, but one that should stand up to modest load
Home-page: UNKNOWN
Author: James Pickering
Author-email: james.pickering@airelogic.com
License: MIT
Platform: UNKNOWN
Classifier: Programming Language :: Python :: 2
Classifier: Programming Language :: Python :: 2.7
Classifier: Programming Language :: Python :: 3
Classifier: Programming Language :: Python :: 3.4
Classifier: Programming Language :: Python :: 3.5
Classifier: Programming Language :: Python :: 3.6
Classifier: Programming Language :: Python :: 3.7
Classifier: Programming Language :: Python :: 3.8
Classifier: Programming Language :: Python :: 3.9
Requires-Python: >=2.7,!=3.0.*,!=3.1.*,!=3.2.*,!=3.3.*
License-File: LICENSE
Requires-Dist: cheroot (>=5.8.3)
Requires-Dist: lmdb (>=0.93)
Requires-Dist: monotonic (>=1.3)
Requires-Dist: six (>=1.10.0)
Requires-Dist: werkzeug (>=0.12.2)
Requires-Dist: wrapt (>=1.10.11)
